syn_fifo/FIFO_memory.v
// Code your design here
module FIFO_memory(clk,reset,din,read,write,dout,empty,full); 
 
	input clk; 
	input reset; 
    input [31:0]din;	//32-bit data input 
	input read; 
	input write; 
 
    output [31:0]dout; //32-bit data output 
	output empty; 	   //flag to indicate that the memory is empty 
	output full;	   //flag to indicate that the memory is full 
	 
	parameter DEPTH=3, MAX_COUNT=3'b111;	 
//DEPTH is number of bits, 3 bits thus 2^3=8 memory locations and MAX_COUNT is the last memory location. 
	 
	reg [31:0]dout; 
	//reg empty; 
	//reg full; 
 
	/*wptr is write_pointer and rptr is read_pointer*/ 
 
	reg [(DEPTH-1):0]rptr;	 
// rptr(3bits) defines memory pointer location for reading instructions(000 or 001....111) 
	 
	reg [(DEPTH-1):0]wptr;	 
// wptr(3bits) defines memory pointer location for writing instructions(000 or 001....111) 
	 
	reg [(DEPTH-1):0]count;	 
// 3 bits count register[000(0),001(1),010(2),....,111(7)] 
	 
	reg [31:0]fifo_mem[0:MAX_COUNT];  
// fifo memory is having 16 bits data and 8 memory locations 
	 

 
///////// WHEN BOTH READING AND WRITING BUT FIFO IS EMPTY //////// 
/* 
	always @(posedge clk) 
		begin 
			if(reset==1) 
			//reset is pressed															 
				sr_read_write_empty <= 0; 
			else if(read==1 && empty==1 && write==1)	 
			//when fifo is empty and read & write both 1 
				sr_read_write_empty <= 1; 
			else 
				sr_read_write_empty <= 0; 
		end 
*/ 
//////////////////////// COUNTER OPERATION /////////////////////// 
		 
	always @(posedge clk) 
		begin 
			if(reset==1) 
//when reset, the fifo is made empty thus count is set to zero 
				count <= 3'b000;		 
			else 
				begin 
					case({read,write}) 
					//CASE-1:when not reading or writing	 
						2'b00:	count <= count;				 
								//count remains same 
					//CASE-2:when writing only 
						2'b01:	if(!full)			 
									count <= count+1; 
									//count increases 
					//CASE-3:when reading only							 
						2'b10:	if(!empty)				 
									count <= count-1;							 
									//count decreases 
					//CASE-4 
						2'b11:	if(empty)	 
									count <= count+1; //(if) fifo is empty => only w
//(if) fifo is empty => only write, thus count increases			 
								else if(full)
									count <= count-1;
								else
									count <= count; 
//(else) both read and write takes place, thus no change											 
					//DEFAULT CASE			 
						default: count <= count;
                    endcase
                end
        end
////////////////////// EMPTY AND FULL ALERT ///////////////////// 
	
	assign empty = (count==3'b000);
	assign full = (count==MAX_COUNT);
	// Memory empty signal 

///////////// READ AND WRITE POINTER MEMORY LOCATION ///////////// 
 
	// Write operation memory pointer 
	always @(posedge clk)
		begin 
			if(reset) 
			//wptr moved to zero location (fifo is made empty) 
				wptr <= 3'b000;	 
			else 
				begin 
					if(write && !full)	 
					//writing when memory is NOT FULL 
						wptr <= wptr+1; 
				end 
		end 
	// Write operation 
	always @(posedge clk) 
		//IT CAN WRITE WHEN RESET IS USED AS FULL==0	 
		begin 
			if(write && !full) 
			//writing when memory is NOT FULL 
				fifo_mem[wptr] <= din; 
			else									 
			//when NOT WRITING 
				fifo_mem[wptr] <= fifo_mem[wptr]; 
		end  
	// Read operation memory pointer 
		always @(posedge clk) 
			begin 
				if(reset) 
				//rptr moved to zero location (fifo is made empty) 
					rptr <= 3'b000;	 
				else 
					begin 
						if(read && !empty)	 
						//reading when memory is NOT ZERO 
							rptr <= rptr+1; 
					end 
			end 
 
//////////////////// READ AND WRITE OPERATION //////////////////// 
 	// Read operation 
	always @(posedge clk) 
		begin 
			if(reset)						 
			//reset implies output is zero 
				dout <= 32'h0000; 
			else if(read && !empty)	 
			//reading data when memory is NOT EMPTY 
				dout <= fifo_mem[rptr]; 
			else 
			//no change 
				dout <= dout;  
		end 
endmodule

syn_fifo/stimulus.v
// Code your testbench here
// or browse Examples
module stimulus;
	reg CLK,
		RESET,
		READ,
		WRITE;
	wire EMPTY,
		 FULL;
	reg [31:0] DIN;
	wire [31:0] DOUT;
	
	FIFO_memory FF1(CLK,RESET,DIN,READ,WRITE,DOUT,EMPTY,FULL);
	initial
		begin
		CLK = 0;
        $dumpfile ("exp.vcd");
		$dumpvars (2,stimulus);
        $monitor("%d  %d",FF1.fifo_mem[0],FF1.fifo_mem[1]);
		RESET=0;READ=0;WRITE=0;
		DIN=32'h0000_0000;
		end
	
	always
	#5 CLK=~CLK;
	
	always
		begin
		#4 RESET=1;
		#4 RESET=0;
        #5 WRITE=1;DIN=$random;
		#11 DIN=$random;
		#11 DIN=$random;
		#11 DIN=$random;
		#11 DIN=$random;
		#11 DIN=$random;
		
		#11 DIN=$random;
		#11 DIN=$random;
		#1 READ = 1;
		#11 DIN=$random;
		#11 DIN=$random;
		#11 DIN=$random;
		#3 WRITE=0;
		#200 $finish;
        end
endmodule

syn_fifo/exp.vcd
$date
	Tue Apr 16 19:50:40 2024
$end
$version
	Icarus Verilog
$end
$timescale
	1s
$end
$scope module stimulus $end
$var wire 1 ! FULL $end
$var wire 1 " EMPTY $end
$var wire 32 # DOUT [31:0] $end
$var reg 1 $ CLK $end
$var reg 32 % DIN [31:0] $end
$var reg 1 & READ $end
$var reg 1 ' RESET $end
$var reg 1 ( WRITE $end
$scope module FF1 $end
$var wire 1 $ clk $end
$var wire 32 ) din [31:0] $end
$var wire 1 & read $end
$var wire 1 ' reset $end
$var wire 1 ( write $end
$var wire 1 ! full $end
$var wire 1 " empty $end
$var reg 3 * count [2:0] $end
$var reg 32 + dout [31:0] $end
$var reg 3 , rptr [2:0] $end
$var reg 3 - wptr [2:0] $end
$upscope $end
$upscope $end
$enddefinitions $end
#0
$dumpvars
bx -
bx ,
bx +
bx *
b0 )
0(
0'
0&
b0 %
0$
bx #
x"
x!
$end
#4
1'
#5
1"
0!
b0 *
b0 -
b0 ,
b0 #
b0 +
1$
#8
0'
#10
0$
#13
b10010000101010011010100100100 %
b10010000101010011010100100100 )
1(
#15
b1 -
0"
b1 *
1$
#20
0$
#24
b11000000100010010101111010000001 %
b11000000100010010101111010000001 )
#25
b10 *
b10 -
1$
#30
0$
#35
b11 -
b11 *
1$
b10000100100001001101011000001001 %
b10000100100001001101011000001001 )
#40
0$
#45
b100 *
b100 -
1$
#46
b10110001111100000101011001100011 %
b10110001111100000101011001100011 )
#50
0$
#55
b101 -
b101 *
1$
#57
b110101110010111101100001101 %
b110101110010111101100001101 )
#60
0$
#65
b110 *
b110 -
1$
#68
b1000110110111111001100110001101 %
b1000110110111111001100110001101 )
#70
0$
#75
b111 -
1!
b111 *
1$
#79
b10110010110000101000010001100101 %
b10110010110000101000010001100101 )
#80
0$
#85
1$
#90
0$
b10001001001101110101001000010010 %
b10001001001101110101001000010010 )
#91
1&
#95
b10010000101010011010100100100 #
b10010000101010011010100100100 +
b1 ,
0!
b110 *
1$
#100
0$
#102
b111100111110001100000001 %
b111100111110001100000001 )
#105
b0 -
b10 ,
b11000000100010010101111010000001 #
b11000000100010010101111010000001 +
1$
#110
0$
#113
b110110101111100110100001101 %
b110110101111100110100001101 )
#115
b10000100100001001101011000001001 #
b10000100100001001101011000001001 +
b11 ,
b1 -
1$
#120
0$
#124
b111011001000111111000101110110 %
b111011001000111111000101110110 )
#125
b10 -
b100 ,
1$
#127
0(
#130
0$
#135
b10110001111100000101011001100011 #
b10110001111100000101011001100011 +
b101 ,
b101 *
1$
#140
0$
#145
b100 *
b110 ,
b110101110010111101100001101 #
b110101110010111101100001101 +
1$
#150
0$
#155
b1000110110111111001100110001101 #
b1000110110111111001100110001101 +
b111 ,
b11 *
1$
#160
0$
#165
b10 *
b0 ,
b111100111110001100000001 #
b111100111110001100000001 +
1$
#170
0$
#175
b110110101111100110100001101 #
b110110101111100110100001101 +
b1 ,
b1 *
1$
#180
0$
#185
1"
b0 *
b10 ,
b111011001000111111000101110110 #
b111011001000111111000101110110 +
1$
